.gitignore
.pylintrc
.readthedocs.yml
CODE_OF_CONDUCT.md
LICENSE
README.rst
circuitpython_parse.py
requirements.txt
setup.py
.github/workflows/build.yml
.github/workflows/release.yml
circuitpython_parse.egg-info/PKG-INFO
circuitpython_parse.egg-info/SOURCES.txt
circuitpython_parse.egg-info/dependency_links.txt
circuitpython_parse.egg-info/requires.txt
circuitpython_parse.egg-info/top_level.txt
docs/api.rst
docs/conf.py
docs/examples.rst
docs/index.rst
docs/_static/favicon.ico
examples/parse_simpletest.py
tests/__init__.py
tests/test_parse.py