Metadata-Version: 2.1
Name: circuitpython-parse
Version: 0.4.0
Summary: Parse (absolute and relative) URLs.
Home-page: https://github.com/JimBobBennett/CircuitPython_Parse
Author: Jim Bennett
Author-email: jim.bennett@microsoft.com
License: MIT
Keywords: adafruit blinka circuitpython micropython parse url
Platform: UNKNOWN
Classifier: Development Status :: 3 - Alpha
Classifier: Intended Audience :: Developers
Classifier: Topic :: Software Development :: Libraries
Classifier: Topic :: System :: Hardware
Classifier: License :: OSI Approved :: MIT License
Classifier: Programming Language :: Python :: 3
Classifier: Programming Language :: Python :: 3.4
Classifier: Programming Language :: Python :: 3.5
